MANIFEST.in
README.md
setup.py
eraInterimDownload.egg-info/PKG-INFO
eraInterimDownload.egg-info/SOURCES.txt
eraInterimDownload.egg-info/dependency_links.txt
eraInterimDownload.egg-info/requires.txt
eraInterimDownload.egg-info/top_level.txt
python/eraInterimDownload.py
python/utils.py