Metadata-Version: 1.1
Name: eraInterimDownload
Version: 0.0.4
Summary: A utility to download ERA INTERIM meteo data 
Home-page: https://github.com/yoannMoreau/eraInterimDownload
Author: Yoann M
Author-email: yoann.moreau@gmail.com
License: CCO
Platform: Posix;
Classifier: Development Status :: 3 - Alpha
